[
    // Cursor Keys
    // -- Alt
    {
        "key": "alt+left",
        "command": "-workbench.action.navigateBack"
    },
    {
        "key": "alt+left",
        "command": "editor.action.outdentLines",
        "when": "editorTextFocus && !editorReadonly"
    },
    {
        "key": "alt+right",
        "command": "-workbench.action.navigateForward"
    },
    {
        "key": "alt+right",
        "command": "editor.action.indentLines",
        "when": "editorTextFocus && !editorReadonly"
    },
    // -- Ctrl + Alt
    {
        "key": "ctrl+alt+up",
        "command": "-editor.action.insertCursorAbove",
        "when": "editorTextFocus"
    },
    {
        "key": "ctrl+alt+up",
        "command": "editor.action.copyLinesUpAction",
        "when": "editorTextFocus && !editorReadonly"
    },
    {
        "key": "ctrl+alt+down",
        "command": "-editor.action.insertCursorBelow",
        "when": "editorTextFocus"
    },
    {
        "key": "ctrl+alt+down",
        "command": "editor.action.copyLinesDownAction",
        "when": "editorTextFocus && !editorReadonly"
    },
    // -- Shift + Alt
    {
        "key": "shift+alt+up",
        "command": "-editor.action.copyLinesUpAction",
        "when": "editorTextFocus && !editorReadonly"
    },
    {
        "key": "shift+alt+up",
        "command": "editor.action.insertCursorAbove",
        "when": "editorTextFocus"
    },
    {
        "key": "shift+alt+down",
        "command": "-editor.action.copyLinesDownAction",
        "when": "editorTextFocus && !editorReadonly"
    },
    {
        "key": "shift+alt+down",
        "command": "editor.action.insertCursorBelow",
        "when": "editorTextFocus"
    },
    // Quit
    {
        "key": "ctrl+shift+w",
        "command": "-workbench.action.closeWindow"
    },
    // Settings
    {
        "key": "ctrl+,",
        "command": "-workbench.action.openSettings"
    },
    {
        "key": "ctrl+,",
        "command": "workbench.action.openSettingsJson"
    },
    // Quick Action
    {
        "key": "ctrl+q",
        "command": "-workbench.action.quit",
        "when": "isLinux"
    },
    {
        "key": "ctrl+q",
        "command": "workbench.action.quickOpenView",
        "when": "isLinux",
    },
    {
        "key": "ctrl+q",
        "command": "workbench.action.quickOpenNavigateNext",
        "when": "isLinux && inQuickOpen"
    },
    // Format Document
    {
        "key": "ctrl+shift+i",
        "command": "-editor.action.formatDocument",
        "when": "isLinux && editorTextFocus && !editorReadonly"
    },
    {
        "key": "shift+alt+f",
        "command": "editor.action.formatDocument",
        "when": "isLinux && editorTextFocus && !editorReadonly"
    },
    // Reset Zoom
    {
        "key": "ctrl+0",
        "command": "-workbench.action.focusSideBar"
    },
    {
        "key": "ctrl+0",
        "command": "workbench.action.zoomReset"
    },
    // Tags
    {
        "key": "alt+t",
        "command": "-extension.ctagsJumpBack",
        "when": "editorTextFocus"
    },
    {
        "key": "alt+t",
        "command": "extension.findCTags",
        "when": "editorTextFocus"
    },
    {
        "key": "ctrl+t",
        "command": "-extension.findCTags",
        "when": "editorTextFocus"
    },
    {
        "key": "shift+alt+t",
        "command": "extension.ctagsJumpBack",
        "when": "editorTextFocus"
    },
    // Align
    {
        "key": "alt+a",
        "command": "simple-alignment.align",
        "when": "editorTextFocus"
    }
]
